Metadata-Version: 2.1
Name: mysystemmonitor
Version: 0.2.0
Summary: A library to monitoring system.
Home-page: https://github.com/onuratakan/mysystemmonitor
Author: Onur Atakan ULUSOY
Author-email: atadogan06@gmail.com
License: MIT
Platform: UNKNOWN
Requires-Python: >= 3
License-File: LICENSE
